README.rst
setup.py
praatclasses/__init__.py
praatclasses/praat.py
praatclasses.egg-info/PKG-INFO
praatclasses.egg-info/SOURCES.txt
praatclasses.egg-info/dependency_links.txt
praatclasses.egg-info/not-zip-safe
praatclasses.egg-info/top_level.txt