Metadata-Version: 1.0
Name: praatclasses
Version: 0.1
Summary: A bunch of praat object classes for python
Home-page: http://github.com/jofrhwld/praatclasses
Author: Josef Fruehwald
Author-email: jofrhwld@gmail.com
License: MIT
Platform: UNKNOWN
